[
  {
    "time": "2025-09-12T18:23:31.793245+08:00",
    "level": "info",
    "platform": "nowcoder",
    "msg": "Start fetching contest: 2025\u725b\u5ba2\u6691\u671f\u591a\u6821\u8bad\u7ec3\u84251 (2025-07-15)"
  },
  {
    "time": "2025-09-12T18:23:31.793857+08:00",
    "level": "warning",
    "platform": "nowcoder",
    "msg": "Contest folder already exists: contests/2025-07-15 2025\u725b\u5ba2\u6691\u671f\u591a\u6821\u8bad\u7ec3\u84251. Skipped."
  },
  {
    "time": "2025-09-12T18:23:31.794354+08:00",
    "level": "info",
    "platform": "nowcoder",
    "msg": "Start fetching contest: 2025\u725b\u5ba2\u6691\u671f\u591a\u6821\u8bad\u7ec3\u84252 (2025-07-17)"
  },
  {
    "time": "2025-09-12T18:23:31.795033+08:00",
    "level": "warning",
    "platform": "nowcoder",
    "msg": "Contest folder already exists: contests/2025-07-17 2025\u725b\u5ba2\u6691\u671f\u591a\u6821\u8bad\u7ec3\u84252. Skipped."
  },
  {
    "time": "2025-09-12T18:23:31.795869+08:00",
    "level": "info",
    "platform": "nowcoder",
    "msg": "Start fetching contest: \"\u73b0\u4ee3\u6c7d\u8f66\u524d\u77bb\u676f\"2025\u725b\u5ba2\u6691\u671f\u591a\u6821\u8bad\u7ec3\u84253 (2025-07-22)"
  },
  {
    "time": "2025-09-12T18:23:31.796728+08:00",
    "level": "warning",
    "platform": "nowcoder",
    "msg": "Contest folder already exists: contests/2025-07-22 \"\u73b0\u4ee3\u6c7d\u8f66\u524d\u77bb\u676f\"2025\u725b\u5ba2\u6691\u671f\u591a\u6821\u8bad\u7ec3\u84253. Skipped."
  },
  {
    "time": "2025-09-12T18:23:31.797581+08:00",
    "level": "info",
    "platform": "nowcoder",
    "msg": "Start fetching contest: 2025\u725b\u5ba2\u6691\u671f\u591a\u6821\u8bad\u7ec3\u84254 (2025-07-24)"
  },
  {
    "time": "2025-09-12T18:23:31.798412+08:00",
    "level": "warning",
    "platform": "nowcoder",
    "msg": "Contest folder already exists: contests/2025-07-24 2025\u725b\u5ba2\u6691\u671f\u591a\u6821\u8bad\u7ec3\u84254. Skipped."
  },
  {
    "time": "2025-09-12T18:23:31.798998+08:00",
    "level": "info",
    "platform": "nowcoder",
    "msg": "Start fetching contest: 2025\u725b\u5ba2\u6691\u671f\u591a\u6821\u8bad\u7ec3\u84255 (2025-07-29)"
  },
  {
    "time": "2025-09-12T18:23:31.799561+08:00",
    "level": "warning",
    "platform": "nowcoder",
    "msg": "Contest folder already exists: contests/2025-07-29 2025\u725b\u5ba2\u6691\u671f\u591a\u6821\u8bad\u7ec3\u84255. Skipped."
  },
  {
    "time": "2025-09-12T18:23:31.800138+08:00",
    "level": "info",
    "platform": "nowcoder",
    "msg": "Start fetching contest: 2025\u725b\u5ba2\u6691\u671f\u591a\u6821\u8bad\u7ec3\u84256 (2025-07-31)"
  },
  {
    "time": "2025-09-12T18:23:31.800793+08:00",
    "level": "warning",
    "platform": "nowcoder",
    "msg": "Contest folder already exists: contests/2025-07-31 2025\u725b\u5ba2\u6691\u671f\u591a\u6821\u8bad\u7ec3\u84256. Skipped."
  },
  {
    "time": "2025-09-12T18:23:31.801553+08:00",
    "level": "info",
    "platform": "nowcoder",
    "msg": "Start fetching contest: \"\u73b0\u4ee3\u6c7d\u8f66\u524d\u77bb\u676f\"2025\u725b\u5ba2\u6691\u671f\u591a\u6821\u8bad\u7ec3\u84257 (2025-08-05)"
  },
  {
    "time": "2025-09-12T18:23:31.802505+08:00",
    "level": "warning",
    "platform": "nowcoder",
    "msg": "Contest folder already exists: contests/2025-08-05 \"\u73b0\u4ee3\u6c7d\u8f66\u524d\u77bb\u676f\"2025\u725b\u5ba2\u6691\u671f\u591a\u6821\u8bad\u7ec3\u84257. Skipped."
  },
  {
    "time": "2025-09-12T18:23:31.803206+08:00",
    "level": "info",
    "platform": "nowcoder",
    "msg": "Start fetching contest: 2025\u725b\u5ba2\u6691\u671f\u591a\u6821\u8bad\u7ec3\u84258 (2025-08-07)"
  },
  {
    "time": "2025-09-12T18:23:31.803850+08:00",
    "level": "warning",
    "platform": "nowcoder",
    "msg": "Contest folder already exists: contests/2025-08-07 2025\u725b\u5ba2\u6691\u671f\u591a\u6821\u8bad\u7ec3\u84258. Skipped."
  },
  {
    "time": "2025-09-12T18:23:31.804453+08:00",
    "level": "info",
    "platform": "nowcoder",
    "msg": "Start fetching contest: \"\u5f71\u77f3Insta360\u676f\"2025\u725b\u5ba2\u6691\u671f\u591a\u6821\u8bad\u7ec3\u84259 (2025-08-12)"
  },
  {
    "time": "2025-09-12T18:23:31.805433+08:00",
    "level": "warning",
    "platform": "nowcoder",
    "msg": "Contest folder already exists: contests/2025-08-12 \"\u5f71\u77f3Insta360\u676f\"2025\u725b\u5ba2\u6691\u671f\u591a\u6821\u8bad\u7ec3\u84259. Skipped."
  },
  {
    "time": "2025-09-12T18:23:31.806414+08:00",
    "level": "info",
    "platform": "nowcoder",
    "msg": "Start fetching contest: \"\u5f71\u77f3Insta360\u676f\"2025\u725b\u5ba2\u6691\u671f\u591a\u6821\u8bad\u7ec3\u842510 (2025-08-14)"
  },
  {
    "time": "2025-09-12T18:23:31.807440+08:00",
    "level": "warning",
    "platform": "nowcoder",
    "msg": "Contest folder already exists: contests/2025-08-14 \"\u5f71\u77f3Insta360\u676f\"2025\u725b\u5ba2\u6691\u671f\u591a\u6821\u8bad\u7ec3\u842510. Skipped."
  },
  {
    "time": "2025-09-12T18:23:31.808321+08:00",
    "level": "info",
    "platform": "nowcoder",
    "msg": "Contests fetched successfully."
  },
  {
    "time": "2025-09-12T18:23:31.809156+08:00",
    "level": "info",
    "platform": "nowcoder",
    "msg": "Start updating staged submissions..."
  },
  {
    "time": "2025-09-12T18:23:31.809908+08:00",
    "level": "info",
    "platform": "nowcoder",
    "msg": "Start fetching new submissions..."
  },
  {
    "time": "2025-09-12T18:23:31.810598+08:00",
    "level": "info",
    "platform": "nowcoder",
    "msg": "Start fetching submissions from https://ac.nowcoder.com/acm/contest/108298."
  },
  {
    "time": "2025-09-12T18:23:34.942490+08:00",
    "level": "warning",
    "platform": "nowcoder",
    "msg": "No submissions found on this page. Probably the contest has not started yet."
  },
  {
    "time": "2025-09-12T18:23:34.943262+08:00",
    "level": "info",
    "platform": "nowcoder",
    "msg": "Start fetching submissions from https://ac.nowcoder.com/acm/contest/108299."
  },
  {
    "time": "2025-09-12T18:23:38.478149+08:00",
    "level": "info",
    "platform": "nowcoder",
    "msg": "Reached last update (Submission 78282935), stopping."
  },
  {
    "time": "2025-09-12T18:23:38.479620+08:00",
    "level": "info",
    "platform": "nowcoder",
    "msg": "Fetched 20 submissions from https://ac.nowcoder.com/acm/contest/108299, page 1."
  },
  {
    "time": "2025-09-12T18:23:38.480346+08:00",
    "level": "info",
    "platform": "nowcoder",
    "msg": "Start fetching submissions from https://ac.nowcoder.com/acm/contest/108300."
  },
  {
    "time": "2025-09-12T18:23:41.622564+08:00",
    "level": "info",
    "platform": "nowcoder",
    "msg": "Reached last update (Submission 78393143), stopping."
  },
  {
    "time": "2025-09-12T18:23:41.623454+08:00",
    "level": "info",
    "platform": "nowcoder",
    "msg": "Fetched 20 submissions from https://ac.nowcoder.com/acm/contest/108300, page 1."
  },
  {
    "time": "2025-09-12T18:23:41.624274+08:00",
    "level": "info",
    "platform": "nowcoder",
    "msg": "Start fetching submissions from https://ac.nowcoder.com/acm/contest/108301."
  },
  {
    "time": "2025-09-12T18:23:44.768075+08:00",
    "level": "info",
    "platform": "nowcoder",
    "msg": "Reached last update (Submission 78634159), stopping."
  },
  {
    "time": "2025-09-12T18:23:44.768982+08:00",
    "level": "info",
    "platform": "nowcoder",
    "msg": "Fetched 20 submissions from https://ac.nowcoder.com/acm/contest/108301, page 1."
  },
  {
    "time": "2025-09-12T18:23:44.769815+08:00",
    "level": "info",
    "platform": "nowcoder",
    "msg": "Start fetching submissions from https://ac.nowcoder.com/acm/contest/108302."
  },
  {
    "time": "2025-09-12T18:23:47.906161+08:00",
    "level": "warning",
    "platform": "nowcoder",
    "msg": "No submissions found on this page. Probably the contest has not started yet."
  },
  {
    "time": "2025-09-12T18:23:47.907022+08:00",
    "level": "info",
    "platform": "nowcoder",
    "msg": "Start fetching submissions from https://ac.nowcoder.com/acm/contest/108303."
  },
  {
    "time": "2025-09-12T18:23:51.042009+08:00",
    "level": "info",
    "platform": "nowcoder",
    "msg": "Reached last update (Submission 79124032), stopping."
  },
  {
    "time": "2025-09-12T18:23:51.042903+08:00",
    "level": "info",
    "platform": "nowcoder",
    "msg": "Fetched 20 submissions from https://ac.nowcoder.com/acm/contest/108303, page 1."
  },
  {
    "time": "2025-09-12T18:23:51.043650+08:00",
    "level": "info",
    "platform": "nowcoder",
    "msg": "Start fetching submissions from https://ac.nowcoder.com/acm/contest/108304."
  },
  {
    "time": "2025-09-12T18:23:54.174891+08:00",
    "level": "warning",
    "platform": "nowcoder",
    "msg": "No submissions found on this page. Probably the contest has not started yet."
  },
  {
    "time": "2025-09-12T18:23:54.175858+08:00",
    "level": "info",
    "platform": "nowcoder",
    "msg": "Start fetching submissions from https://ac.nowcoder.com/acm/contest/108305."
  },
  {
    "time": "2025-09-12T18:23:57.318475+08:00",
    "level": "warning",
    "platform": "nowcoder",
    "msg": "No submissions found on this page. Probably the contest has not started yet."
  },
  {
    "time": "2025-09-12T18:23:57.319409+08:00",
    "level": "info",
    "platform": "nowcoder",
    "msg": "Start fetching submissions from https://ac.nowcoder.com/acm/contest/108306."
  },
  {
    "time": "2025-09-12T18:24:00.462697+08:00",
    "level": "info",
    "platform": "nowcoder",
    "msg": "Reached last update (Submission 78843710), stopping."
  },
  {
    "time": "2025-09-12T18:24:00.463595+08:00",
    "level": "info",
    "platform": "nowcoder",
    "msg": "Fetched 20 submissions from https://ac.nowcoder.com/acm/contest/108306, page 1."
  },
  {
    "time": "2025-09-12T18:24:00.464435+08:00",
    "level": "info",
    "platform": "nowcoder",
    "msg": "Start fetching submissions from https://ac.nowcoder.com/acm/contest/108307."
  },
  {
    "time": "2025-09-12T18:24:03.603419+08:00",
    "level": "warning",
    "platform": "nowcoder",
    "msg": "No submissions found on this page. Probably the contest has not started yet."
  },
  {
    "time": "2025-09-12T18:24:03.604504+08:00",
    "level": "info",
    "platform": "nowcoder",
    "msg": "Submissions fetched successfully."
  },
  {
    "time": "2025-09-12T18:24:03.605350+08:00",
    "level": "important",
    "platform": "nowcoder",
    "msg": "nowcoder Crawler finished successfully at 2025-09-12T18:24:03.605344+08:00"
  }
]