[
  {
    "time": "2025-09-19T04:13:34.737945+08:00",
    "level": "info",
    "platform": "qoj",
    "msg": "Submissions fetched successfully."
  },
  {
    "time": "2025-09-19T04:13:34.738581+08:00",
    "level": "important",
    "platform": "qoj",
    "msg": "QOJ Crawler finished successfully at 2025-09-19T04:13:34.738575+08:00"
  },
  {
    "time": "2025-09-20T04:11:38.233217+08:00",
    "level": "warning",
    "platform": "qoj",
    "msg": "Download directory does not exist, creating it."
  },
  {
    "time": "2025-09-20T04:11:38.819410+08:00",
    "level": "important",
    "platform": "qoj",
    "msg": "QOJ Crawler started at 2025-09-20T04:11:38.819394+08:00"
  },
  {
    "time": "2025-09-20T04:11:43.163457+08:00",
    "level": "info",
    "platform": "qoj",
    "msg": "Login successful with username and password."
  },
  {
    "time": "2025-09-20T04:11:45.947820+08:00",
    "level": "info",
    "platform": "qoj",
    "msg": "Contest list is empty, no contests to fetch. Exiting."
  },
  {
    "time": "2025-09-20T04:11:45.948540+08:00",
    "level": "info",
    "platform": "qoj",
    "msg": "Contests fetched successfully."
  },
  {
    "time": "2025-09-20T04:11:45.949763+08:00",
    "level": "info",
    "platform": "qoj",
    "msg": "Start updating staged submissions..."
  },
  {
    "time": "2025-09-20T04:11:45.952782+08:00",
    "level": "info",
    "platform": "qoj",
    "msg": "Start fetching new submissions..."
  },
  {
    "time": "2025-09-20T04:11:45.953405+08:00",
    "level": "info",
    "platform": "qoj",
    "msg": "Start fetching submissions from page 1."
  },
  {
    "time": "2025-09-20T04:11:48.951247+08:00",
    "level": "info",
    "platform": "qoj",
    "msg": "Reached last update (Submission #1359155), stopping."
  },
  {
    "time": "2025-09-20T04:11:48.951968+08:00",
    "level": "info",
    "platform": "qoj",
    "msg": "Submissions fetched successfully."
  },
  {
    "time": "2025-09-20T04:11:48.952547+08:00",
    "level": "important",
    "platform": "qoj",
    "msg": "QOJ Crawler finished successfully at 2025-09-20T04:11:48.952541+08:00"
  },
  {
    "time": "2025-09-26T04:12:54.251653+08:00",
    "level": "warning",
    "platform": "qoj",
    "msg": "Download directory does not exist, creating it."
  },
  {
    "time": "2025-09-26T04:12:54.793568+08:00",
    "level": "important",
    "platform": "qoj",
    "msg": "QOJ Crawler started at 2025-09-26T04:12:54.793551+08:00"
  },
  {
    "time": "2025-09-26T04:12:59.801321+08:00",
    "level": "info",
    "platform": "qoj",
    "msg": "Login successful with username and password."
  },
  {
    "time": "2025-09-26T04:13:02.616653+08:00",
    "level": "info",
    "platform": "qoj",
    "msg": "Start fetching contest: The 2021 ICPC Asia Macau Regional Contest (2025-09-25)"
  },
  {
    "time": "2025-09-26T04:13:02.617462+08:00",
    "level": "info",
    "platform": "qoj",
    "msg": "Created contest folder: contests/2025-09-25 The 2021 ICPC Asia Macau Regional Contest"
  },
  {
    "time": "2025-09-26T04:13:59.895399+08:00",
    "level": "info",
    "platform": "qoj",
    "msg": "Finished fetching contest: The 2021 ICPC Asia Macau Regional Contest (2025-09-25)"
  },
  {
    "time": "2025-09-26T04:13:59.896082+08:00",
    "level": "info",
    "platform": "qoj",
    "msg": "Contests fetched successfully."
  },
  {
    "time": "2025-09-26T04:13:59.897258+08:00",
    "level": "info",
    "platform": "qoj",
    "msg": "Start updating staged submissions..."
  },
  {
    "time": "2025-09-26T04:13:59.900400+08:00",
    "level": "info",
    "platform": "qoj",
    "msg": "Start fetching new submissions..."
  },
  {
    "time": "2025-09-26T04:13:59.901008+08:00",
    "level": "info",
    "platform": "qoj",
    "msg": "Start fetching submissions from page 1."
  },
  {
    "time": "2025-09-26T04:14:05.239797+08:00",
    "level": "info",
    "platform": "qoj",
    "msg": "Fetched 10 submissions from page 1."
  },
  {
    "time": "2025-09-26T04:14:05.240386+08:00",
    "level": "info",
    "platform": "qoj",
    "msg": "Start fetching submissions from page 2."
  },
  {
    "time": "2025-09-26T04:14:07.147902+08:00",
    "level": "info",
    "platform": "qoj",
    "msg": "Fetched 10 submissions from page 2."
  },
  {
    "time": "2025-09-26T04:14:07.148486+08:00",
    "level": "info",
    "platform": "qoj",
    "msg": "Start fetching submissions from page 3."
  },
  {
    "time": "2025-09-26T04:14:08.504187+08:00",
    "level": "info",
    "platform": "qoj",
    "msg": "Fetched 10 submissions from page 3."
  },
  {
    "time": "2025-09-26T04:14:08.505183+08:00",
    "level": "info",
    "platform": "qoj",
    "msg": "Start fetching submissions from page 4."
  },
  {
    "time": "2025-09-26T04:14:09.909359+08:00",
    "level": "info",
    "platform": "qoj",
    "msg": "Fetched 10 submissions from page 4."
  },
  {
    "time": "2025-09-26T04:14:09.910049+08:00",
    "level": "info",
    "platform": "qoj",
    "msg": "Start fetching submissions from page 5."
  },
  {
    "time": "2025-09-26T04:14:15.402744+08:00",
    "level": "info",
    "platform": "qoj",
    "msg": "Fetched 10 submissions from page 5."
  },
  {
    "time": "2025-09-26T04:14:15.403449+08:00",
    "level": "info",
    "platform": "qoj",
    "msg": "Start fetching submissions from page 6."
  },
  {
    "time": "2025-09-26T04:14:25.097863+08:00",
    "level": "info",
    "platform": "qoj",
    "msg": "Fetched 10 submissions from page 6."
  },
  {
    "time": "2025-09-26T04:14:25.098563+08:00",
    "level": "info",
    "platform": "qoj",
    "msg": "Start fetching submissions from page 7."
  },
  {
    "time": "2025-09-26T04:14:27.123378+08:00",
    "level": "info",
    "platform": "qoj",
    "msg": "Fetched 10 submissions from page 7."
  },
  {
    "time": "2025-09-26T04:14:27.124113+08:00",
    "level": "info",
    "platform": "qoj",
    "msg": "Start fetching submissions from page 8."
  },
  {
    "time": "2025-09-26T04:14:28.911875+08:00",
    "level": "info",
    "platform": "qoj",
    "msg": "Fetched 10 submissions from page 8."
  },
  {
    "time": "2025-09-26T04:14:28.912603+08:00",
    "level": "info",
    "platform": "qoj",
    "msg": "Start fetching submissions from page 9."
  },
  {
    "time": "2025-09-26T04:14:29.613105+08:00",
    "level": "info",
    "platform": "qoj",
    "msg": "Fetched 10 submissions from page 9."
  },
  {
    "time": "2025-09-26T04:14:29.613908+08:00",
    "level": "info",
    "platform": "qoj",
    "msg": "Start fetching submissions from page 10."
  },
  {
    "time": "2025-09-26T04:14:30.504344+08:00",
    "level": "info",
    "platform": "qoj",
    "msg": "Fetched 10 submissions from page 10."
  },
  {
    "time": "2025-09-26T04:14:30.505045+08:00",
    "level": "info",
    "platform": "qoj",
    "msg": "Start fetching submissions from page 11."
  },
  {
    "time": "2025-09-26T04:14:31.167579+08:00",
    "level": "info",
    "platform": "qoj",
    "msg": "Fetched 10 submissions from page 11."
  },
  {
    "time": "2025-09-26T04:14:31.168369+08:00",
    "level": "info",
    "platform": "qoj",
    "msg": "Start fetching submissions from page 12."
  },
  {
    "time": "2025-09-26T04:14:32.847057+08:00",
    "level": "info",
    "platform": "qoj",
    "msg": "Fetched 10 submissions from page 12."
  },
  {
    "time": "2025-09-26T04:14:32.847845+08:00",
    "level": "info",
    "platform": "qoj",
    "msg": "Start fetching submissions from page 13."
  },
  {
    "time": "2025-09-26T04:14:34.561589+08:00",
    "level": "info",
    "platform": "qoj",
    "msg": "Reached last update (Submission #1363219), stopping."
  },
  {
    "time": "2025-09-26T04:14:34.562623+08:00",
    "level": "info",
    "platform": "qoj",
    "msg": "Submissions fetched successfully."
  },
  {
    "time": "2025-09-26T04:14:34.563424+08:00",
    "level": "important",
    "platform": "qoj",
    "msg": "QOJ Crawler finished successfully at 2025-09-26T04:14:34.563418+08:00"
  }
]